jetpack/chat/artifacts.html
jetpack/chat/chat_completions.py
jetpack/chat/chat_messages.html
jetpack/chat/chat_queries.py
jetpack/chat/chat_wit.py
jetpack/coder/coder_completions.py
jetpack/coder/coder_wit.py
jetpack/coder/retriever_completions.py
jetpack/coder/retriever_wit.py
jetpack/design/design.css
jetpack/design/design.html
jetpack/frontend/frontend_queries.py
jetpack/frontend/frontend_wit.py
jetpack/frontend/index.html
jetpack/messages/__init__.py
jetpack/messages/messages_chat.py
jetpack/messages/messages_coder.py
jetpack/sync.toml
jetpack/tailwind.config.js
completions/__init__.py
completions/completion_helpers.py
completions/function_builder.py
completions/prompt_builder.py
tools/__init__.py
tools/data_parser.py
tools/store_wrapper.py
cli/aos.py
grit/__init__.py
grit/object_model.py
grit/object_model_v2.py
grit/object_serialization.py
grit/object_store.py
grit/references.py
grit/stores/__init__.py
grit/stores/file/__init__.py
grit/stores/file/file_object_store.py
grit/stores/file/file_references.py
grit/stores/lmdb/__init__.py
grit/stores/lmdb/lmdb_object_store.py
grit/stores/lmdb/lmdb_references.py
grit/stores/lmdb/shared_env.py
grit/stores/memory/__init__.py
grit/stores/memory/memory_object_store.py
grit/stores/memory/memory_references.py
grit/tree_helpers.py
runtime/__init__.py
runtime/actor_executor.py
runtime/core_loader.py
runtime/query_executor.py
runtime/request_response_executor.py
runtime/resolvers.py
runtime/runtime.py
runtime/runtime_executor.py
sync/__init__.py
sync/actor_push.py
sync/sync_file.py
sync/sync_item.py
web/__init__.py
web/web_server.py
wit/__init__.py
wit/data_model.py
wit/data_model_utils.py
wit/errors.py
wit/prototype.py
wit/query.py
wit/request_response.py
wit/wit_api.py
wit/wit_routers.py
wit/wit_state.py
wit/wut.py
agent_os_py-0.1.1.dist-info/LICENSE.txt
agent_os_py-0.1.1.dist-info/METADATA
agent_os_py-0.1.1.dist-info/WHEEL
agent_os_py-0.1.1.dist-info/entry_points.txt
agent_os_py-0.1.1.dist-info/RECORD
