Metadata-Version: 2.1
Name: agent-os-py
Version: 0.1.1
Summary: A library and runtime to build autonomous AI agents.
Home-page: https://github.com/lukebuehler/agent-os
License: MIT
Requires-Python: >=3.10,<4.0
Classifier: License :: OSI Approved :: MIT License
Classifier: Programming Language :: Python :: 3
Classifier: Programming Language :: Python :: 3.10
Classifier: Programming Language :: Python :: 3.11
Classifier: Programming Language :: Python :: 3.12
Requires-Dist: aiofiles (>=23.1.0,<24.0.0)
Requires-Dist: async-lru (>=2.0.2,<3.0.0)
Requires-Dist: click (>=8.1.5,<9.0.0)
Requires-Dist: filetype (>=1.2.0,<2.0.0)
Requires-Dist: lmdb (>=1.4.1,<2.0.0)
Requires-Dist: pydantic (>=2.0.1,<3.0.0)
Requires-Dist: pytest-asyncio (>=0.21.0,<0.22.0)
Requires-Dist: python-dotenv (>=1.0.0,<2.0.0)
Requires-Dist: sse-starlette (>=1.6.1,<2.0.0)
Requires-Dist: starlette (>=0.28.0,<0.29.0)
Requires-Dist: tomlkit (>=0.11.8,<0.12.0)
Requires-Dist: uvicorn (>=0.22.0,<0.23.0)
Requires-Dist: watchfiles (>=0.19.0,<0.20.0)
Project-URL: Repository, https://github.com/lukebuehler/agent-os
